README.rst
setup.py
bin/gae-flightdeck
gae_flightdeck.egg-info/PKG-INFO
gae_flightdeck.egg-info/SOURCES.txt
gae_flightdeck.egg-info/dependency_links.txt
gae_flightdeck.egg-info/entry_points.txt
gae_flightdeck.egg-info/not-zip-safe
gae_flightdeck.egg-info/requires.txt
gae_flightdeck.egg-info/top_level.txt
gaeflightdeck/__init__.py
gaeflightdeck/formatter.py
gaeflightdeck/server.py
gaeflightdeck/web_server.py