Metadata-Version: 1.0
Name: gae-flightdeck
Version: 0.0.1
Summary: Web-based log viewer for App Engine local development server.
Home-page: http://jonparrott.com
Author: Jon Wayne Parrott
Author-email: jjramone13@gmail.com
License: Apache License, Version 2.0
Keywords: goolge app engine gevent logs
Platform: UNKNOWN
